api_2b2t.py
api_2b2t-1.0.4.dist-info/WHEEL
api_2b2t-1.0.4.dist-info/METADATA
api_2b2t-1.0.4.dist-info/RECORD
